servi_tenant_resolver/__init__.py
servi_tenant_resolver/deps.py
servi_tenant_resolver/middleware.py
servi_tenant_resolver-0.1.2.dist-info/METADATA
servi_tenant_resolver-0.1.2.dist-info/WHEEL
servi_tenant_resolver-0.1.2.dist-info/RECORD
