Metadata-Version: 2.4
Name: servi-tenant-resolver
Version: 0.1.2
Summary: Una librería para gestionar multitenancy por schema en FastAPI con soporte síncrono y asíncrono.
Project-URL: Homepage, https://github.com/tu-usuario/servi-tenant-resolver
Project-URL: Issues, https://github.com/tu-usuario/servi-tenant-resolver/issues
Author-email: Aldair De Hoyos <aldair.dehoyos@servinformacion.com>
Classifier: Development Status :: 4 - Beta
Classifier: Framework :: FastAPI
Classifier: Intended Audience :: Developers
Classifier: License :: OSI Approved :: MIT License
Classifier: Operating System :: OS Independent
Classifier: Programming Language :: Python :: 3
Classifier: Programming Language :: Python :: 3.12
Classifier: Topic :: Database
Classifier: Topic :: Software Development :: Libraries :: Python Modules
Requires-Python: >=3.12
Requires-Dist: fastapi[standard]
Requires-Dist: sqlalchemy[asyncio]
